zipagent/__init__.py
zipagent/agent.py
zipagent/context.py
zipagent/exceptions.py
zipagent/litellm_model.py
zipagent/mcp_tool.py
zipagent/model.py
zipagent/runner.py
zipagent/stream.py
zipagent/system.md
zipagent/tool.py
zipagent-0.1.9.dist-info/METADATA
zipagent-0.1.9.dist-info/WHEEL
zipagent-0.1.9.dist-info/licenses/LICENSE
zipagent-0.1.9.dist-info/RECORD
