Metadata-Version: 2.4
Name: zipagent
Version: 0.1.9
Summary: 轻量级的 AI Agent 框架
Project-URL: Homepage, https://github.com/JiayuXu0/ZipAgent
Project-URL: Repository, https://github.com/JiayuXu0/ZipAgent.git
Project-URL: Issues, https://github.com/JiayuXu0/ZipAgent/issues
Author-email: Jiayu Xu <420249001@qq.com>
Maintainer-email: Jiayu Xu <420249001@qq.com>
License: MIT
License-File: LICENSE
Keywords: agent,ai,assistant,framework,llm
Classifier: Development Status :: 3 - Alpha
Classifier: Intended Audience :: Developers
Classifier: License :: OSI Approved :: MIT License
Classifier: Operating System :: OS Independent
Classifier: Programming Language :: Python
Classifier: Programming Language :: Python :: 3
Classifier: Programming Language :: Python :: 3.10
Classifier: Programming Language :: Python :: 3.11
Classifier: Programming Language :: Python :: 3.12
Classifier: Topic :: Scientific/Engineering :: Artificial Intelligence
Classifier: Topic :: Software Development :: Libraries :: Python Modules
Requires-Python: >=3.10
Requires-Dist: mcp>=1.12.4
Requires-Dist: nest-asyncio>=1.6.0
Requires-Dist: openai>=1.0.0
Requires-Dist: pydantic>=2.0.0
Provides-Extra: all
Requires-Dist: python-dotenv>=1.0.0; extra == 'all'
Provides-Extra: dev
Requires-Dist: matplotlib>=3.10.5; extra == 'dev'
Requires-Dist: mkdocs-material>=9.5.3; extra == 'dev'
Requires-Dist: mkdocs>=1.5.3; extra == 'dev'
Requires-Dist: pyright>=1.1.350; extra == 'dev'
Requires-Dist: pytest-asyncio>=0.21.0; extra == 'dev'
Requires-Dist: pytest-cov>=4.0.0; extra == 'dev'
Requires-Dist: pytest>=7.0.0; extra == 'dev'
Requires-Dist: ruff>=0.1.0; extra == 'dev'
